alibabacloud_dms_mcp_server_inner/__init__.py
alibabacloud_dms_mcp_server_inner/server.py
alibabacloud_dms_mcp_server_inner-0.1.3.dist-info/METADATA
alibabacloud_dms_mcp_server_inner-0.1.3.dist-info/WHEEL
alibabacloud_dms_mcp_server_inner-0.1.3.dist-info/entry_points.txt
alibabacloud_dms_mcp_server_inner-0.1.3.dist-info/RECORD
