Metadata-Version: 2.4
Name: alibabacloud-dms-mcp-server-inner
Version: 0.1.3
Summary: MCP Server for DMS
Author: DMS
Requires-Python: >=3.10
Requires-Dist: httpx>=0.28.1
Requires-Dist: mcp[cli]>=1.8.1
